cxregions/__init__.py
cxregions/curves.py
cxregions/mobius.py
cxregions/paths.py
cxregions/regions.py
cxregions-0.1.5.dist-info/METADATA
cxregions-0.1.5.dist-info/WHEEL
cxregions-0.1.5.dist-info/licenses/LICENSE
cxregions-0.1.5.dist-info/RECORD
