Metadata-Version: 2.4
Name: cxregions
Version: 0.1.5
Summary: A Python interface to the ComplexRegions.jl Julia package
Project-URL: Homepage, https://github.com/complexvariables/cxregions
Author-email: Toby Driscoll <driscoll@udel.edu>
License-Expression: MIT
License-File: LICENSE
Classifier: License :: OSI Approved :: MIT License
Classifier: Operating System :: OS Independent
Classifier: Programming Language :: Python :: 3
Requires-Python: >=3.11
Requires-Dist: juliacall<0.10,>=0.9.30
Requires-Dist: numpy<3,>=2.1
Requires-Dist: quartodoc<0.12,>=0.11.1
